AUTHORS.rst
CONTRIBUTING.rst
HISTORY.rst
LICENSE
MANIFEST.in
README.rst
setup.cfg
setup.py
docs/Makefile
docs/authors.rst
docs/conf.py
docs/contributing.rst
docs/history.rst
docs/index.rst
docs/installation.rst
docs/make.bat
docs/readme.rst
docs/usage.rst
mkdocs_github_dashboard/__init__.py
mkdocs_github_dashboard/mkdocs_github_dashboard.py
mkdocs_github_dashboard.egg-info/PKG-INFO
mkdocs_github_dashboard.egg-info/SOURCES.txt
mkdocs_github_dashboard.egg-info/dependency_links.txt
mkdocs_github_dashboard.egg-info/entry_points.txt
mkdocs_github_dashboard.egg-info/not-zip-safe
mkdocs_github_dashboard.egg-info/requires.txt
mkdocs_github_dashboard.egg-info/top_level.txt
tests/__init__.py
tests/test_mkdocs_github_dashboard.py