Metadata-Version: 2.1
Name: mkdocs-github-dashboard
Version: 0.2.3
Summary: Python Boilerplate contains all the boilerplate you need to create a Python package.
Home-page: https://github.com/hakuturu583/mkdocs_github_dashboard
Author: mkdocs-github-dashboard
Author-email: ms.kataoka@gmail.com
License: Apache Software License 2.0
Keywords: mkdocs_github_dashboard
Platform: UNKNOWN
Classifier: Development Status :: 2 - Pre-Alpha
Classifier: Intended Audience :: Developers
Classifier: License :: OSI Approved :: Apache Software License
Classifier: Natural Language :: English
Classifier: Programming Language :: Python :: 3
Classifier: Programming Language :: Python :: 3.6
Classifier: Programming Language :: Python :: 3.7
Classifier: Programming Language :: Python :: 3.8
Requires-Python: >=3.6
License-File: LICENSE
License-File: AUTHORS.rst
